MANIFEST.in
README.rst
setup.py
instascrape/__init__.py
instascrape/helpers.py
instascrape.egg-info/PKG-INFO
instascrape.egg-info/SOURCES.txt
instascrape.egg-info/dependency_links.txt
instascrape.egg-info/not-zip-safe
instascrape.egg-info/requires.txt
instascrape.egg-info/top_level.txt