Metadata-Version: 1.0
Name: instascrape
Version: 0.1
Summary: Instagram Scraper written in Python. Mainly able to scrape # of followers, email addresses and biographies for now
Home-page: https://github.com/juliusdanek/instascrape
Author: Julius Danek
Author-email: juliusdanek@gmail.com
License: MIT
Keywords: instagram scraper python biography
Platform: UNKNOWN
